Metadata-Version: 2.1
Name: cbot-client
Version: 0.0.4.dev0
Summary: cBot helper is a simple command line tool for helping contributing recipes in the cBot index repository
Home-page: https://conan.io
Author: JFrog LTD
Author-email: luism@jfrog.com
License: MIT
Keywords: C/C++,package,libraries,developer,manager,dependency,tool,c,c++,cpp
Platform: UNKNOWN
Classifier: Development Status :: 5 - Production/Stable
Classifier: Intended Audience :: Developers
Classifier: Topic :: Software Development :: Build Tools
Classifier: License :: OSI Approved :: MIT License
Classifier: Programming Language :: Python :: 2
Classifier: Programming Language :: Python :: 2.7
Classifier: Programming Language :: Python :: 3
Classifier: Programming Language :: Python :: 3.6
